{"widgetLabel":"المخطط","undo":"تراجع","redo":"إعادة","draw":{"point":"رسم نقطة","polygon":"رسم مضلع","polyline":"رسم متعدد الخطوط","circle":"رسم دائرة","rectangle":"رسم مستطيل","multipoint":"رسم متعدد النقاط","mesh":"رسم شبكة","freehandPolyline":"رسم خط متعدد الخطوط (بشكل يدوي)","freehandPolygon":"رسم مضلع (بشكل يدوي)","text":"إضافة نص"},"digitizers":{"root-point":"رسم نقطة","root-polygon":"رسم مضلع","root-polyline":"رسم متعدد الخطوط","root-circle":"رسم دائرة أو قطع ناقص","root-rectangle":"رسم مستطيل أو مربع","root-multipoint":"رسم متعدد النقاط","root-mesh":"رسم شبكة","root-text":"إضافة نص","leaf-point":"نقطة","leaf-distance-distance":"المسافة-المسافة (تقاطع دائرة-دائرة)","leaf-direction-distance":"الاتجاه-المسافة (تقاطع دائرة-خط)","leaf-direction-direction":"الاتجاه-الاتجاه (تقاطع خط-خط)","leaf-point-segment":"مقطع خطي","leaf-autocomplete":"إكمال تلقائي","leaf-right-angle":"مقطع بزاوية قائمة","leaf-freehand":"مقطع مرسوم يدويًا","leaf-tangent-arc":"مقطع منحنى مماسي","leaf-circular-arc":"مقطع قوسي","leaf-endpoint-arc":"مقطع قوسي بنقطة نهاية","leaf-bezier":"مقطع منحنى بيزيه"},"partActions":{"completePart":"إنهاء جزء","completeInput":"إنهاء الإدخال الحالي","releaseManipulator":"إيقاف متابعة المؤشر","captureManipulator":"متابعة المؤشر","completeDrawing":"إنهاء","cancelDrawing":"إلغاء الأمر"},"keyboardFeedback":{"tooltip":"سرعة الحركة عبر لوحة المفاتيح: {value}{unit}","value":"{value}{unitCompact}"},"tooltips":{"shortcutMessage":"{originalTooltip} (مفتاح الاختصار)"},"advancedSettings":{"keyboardInput":"تمكين اختصارات لوحة المفاتيح المتقدمة"},"selectedCount":"تحديد: {count}","selectedCountTruncated":"{truncated}+","deleteFeature":"حذف المعلم","deleteFeatures":"حذف معالم","selectFeature":"حدد المعلم","duplicateFeature":"تكرار معلم","duplicateFeatures":"تكرار معالم"}